setup.py
t_data_structures/__init__.py
t_data_structures/singleton.py
t_data_structures.egg-info/PKG-INFO
t_data_structures.egg-info/SOURCES.txt
t_data_structures.egg-info/dependency_links.txt
t_data_structures.egg-info/top_level.txt
t_data_structures.egg-info/zip-safe