Metadata-Version: 1.0
Name: t-data-structures
Version: 0.1
Summary: T data structures library
Home-page: https://gitlab.com/ddmello/lib/python/t_data_structures.git
Author: Darrin D'Mello
Author-email: darrin.dmello@gmail.com
License: MIT
Platform: UNKNOWN
